pyworkshift-1.1.2.dist-info/licenses/LICENSE
test/__init__.py
test/base_test.py
test/test_snap_schedule.py
test/test_snippet.py
test/test_work_schedule.py
pyworkshift-1.1.2.dist-info/METADATA
pyworkshift-1.1.2.dist-info/WHEEL
pyworkshift-1.1.2.dist-info/top_level.txt
pyworkshift-1.1.2.dist-info/RECORD
