Metadata-Version: 2.4
Name: PyWorkShift
Version: 1.1.2
Summary: A work schedule library for shifts.
Home-page: https://github.com/point85/PyShift
Author: Kent Randall
Author-email: Kent Randall <point85.llc@gmail.com>
Project-URL: Homepage, https://github.com/point85/PyShift
Project-URL: Issues, https://github.com/point85/PyShift/issues
Keywords: shift,work schedule,shift calendar,work calendar
Classifier: Programming Language :: Python :: 3
Classifier: License :: OSI Approved :: MIT License
Classifier: Operating System :: OS Independent
Requires-Python: >=3.9
License-File: LICENSE
Dynamic: author
Dynamic: home-page
Dynamic: license-file
Dynamic: requires-python
